setup.py
dataloader/__init__.py
dataloader/dataloader.py
dataloader/datatest.py
dataloader/mult_nn.py
dataloader/termcolor.py
dataloader.egg-info/PKG-INFO
dataloader.egg-info/SOURCES.txt
dataloader.egg-info/dependency_links.txt
dataloader.egg-info/not-zip-safe
dataloader.egg-info/top_level.txt