Metadata-Version: 1.0
Name: dataloader
Version: 1.2
Summary: Implements a general purpose data loader for python non-sequential machine learning tasks.
Home-page: http://aarontuor.xyz
Author: Aaron Tuor
Author-email: tuora@students.wwu.edu
License: none
Platform: UNKNOWN
